{
  "code": 200,
  "data": {
    "description": "",
    "html": "<html><head><meta name=\"color-scheme\" content=\"light dark\"></head><body><pre style=\"word-wrap: break-word; white-space: pre-wrap;\">export type UserRole = 'MCLUB_STAFF' | 'SME_OWNER' | 'AGENT' | 'END_USER';\nexport type OrderStatus = 'PENDING' | 'IN_PROGRESS' | 'COMPLETED' | 'SETTLED';\nexport type MemberLevel = 'PLAN_A' | 'PLAN_B' | 'PLAN_C' | 'FULL';\nexport type CommissionStatus = 'PENDING' | 'PAID';\n\nexport interface User {\n  id: string;\n  email: string;\n  name: string;\n  phone: string | null;\n  role: UserRole;\n  avatar: string | null;\n  referredById: string | null;\n  referredBy?: { id: string; name: string } | null;\n  ownedProducts?: { id: string; name: string }[];\n  createdAt: string;\n}\n\nexport interface Product {\n  id: string;\n  name: string;\n  category: string;\n  description: string;\n  keyPoints: string;\n  minInvestment: string | null;\n  smeOwnerId: string;\n  commissionRules: string;\n  icon: string | null;\n  color: string | null;\n  smeOwner?: { id: string; name: string };\n  orderCount?: number;\n}\n\nexport interface Client {\n  id: string;\n  name: string;\n  phone: string | null;\n  email: string | null;\n  source: string | null;\n  memberLevel: MemberLevel;\n  notes: string | null;\n  agentId: string;\n  agent?: { id: string; name: string };\n  totalSpent: number;\n  orders?: OrderWithProduct[];\n  timelineEvents?: TimelineEvent[];\n  createdAt: string;\n}\n\nexport interface Order {\n  id: string;\n  productId: string;\n  endUserId: string;\n  clientId: string;\n  agentId: string | null;\n  status: OrderStatus;\n  amount: number;\n  currency: string;\n  notes: string | null;\n  commissionSettled: boolean;\n  product?: { id: string; name: string; icon: string | null; color: string | null };\n  endUser?: { id: string; name: string };\n  client?: { id: string; name: string; memberLevel?: MemberLevel };\n  agent?: { id: string; name: string };\n  createdAt: string;\n}\n\nexport type OrderWithProduct = Order;\n\nexport interface Commission {\n  id: string;\n  orderId: string;\n  recipientId: string;\n  role: UserRole;\n  amount: number;\n  status: CommissionStatus;\n  order?: {\n    id: string;\n    product?: { id: string; name: string; icon: string | null };\n    client?: { id: string; name: string };\n  };\n  recipient?: { id: string; name: string; role: UserRole };\n  createdAt: string;\n}\n\nexport interface TimelineEvent {\n  id: string;\n  clientId: string;\n  orderId: string | null;\n  eventType: string;\n  title: string;\n  description: string | null;\n  createdById: string | null;\n  createdBy?: { id: string; name: string } | null;\n  order?: { id: string; amount: number; status: string } | null;\n  createdAt: string;\n}\n\nexport type ViewId = string;\n\nexport interface NavItem {\n  id: ViewId;\n  label: string;\n  icon: string;\n}\n\nexport const MCLUB_NAV: NavItem[] = [\n  { id: 'overview', label: '總覽', icon: 'LayoutDashboard' },\n  { id: 'clients', label: '客戶管理', icon: 'Users' },\n  { id: 'orders', label: '訂單管理', icon: 'FileText' },\n  { id: 'products', label: '產品管理', icon: 'Package' },\n  { id: 'users', label: '用戶管理', icon: 'UserCog' },\n  { id: 'commissions', label: '佣金管理', icon: 'Coins' },\n];\n\nexport const SME_NAV: NavItem[] = [\n  { id: 'overview', label: '總覽', icon: 'LayoutDashboard' },\n  { id: 'products', label: '我的產品', icon: 'Package' },\n  { id: 'orders', label: '訂單', icon: 'FileText' },\n  { id: 'commissions', label: '收入', icon: 'Coins' },\n];\n\nexport const AGENT_NAV: NavItem[] = [\n  { id: 'overview', label: '總覽', icon: 'LayoutDashboard' },\n  { id: 'clients', label: '我的客戶', icon: 'Users' },\n  { id: 'commissions', label: '佣金', icon: 'Coins' },\n  { id: 'products', label: '產品資訊', icon: 'Package' },\n];\n\nexport const ENDUSER_NAV: NavItem[] = [\n  { id: 'overview', label: '總覽', icon: 'LayoutDashboard' },\n  { id: 'products', label: '我的產品', icon: 'Package' },\n  { id: 'membership', label: '會員等級', icon: 'Crown' },\n];\n\nexport function getNavForRole(role: UserRole): NavItem[] {\n  switch (role) {\n    case 'MCLUB_STAFF': return MCLUB_NAV;\n    case 'SME_OWNER': return SME_NAV;\n    case 'AGENT': return AGENT_NAV;\n    case 'END_USER': return ENDUSER_NAV;\n  }\n}\n\nexport const STATUS_LABELS: Record<OrderStatus, string> = {\n  PENDING: '待確認',\n  IN_PROGRESS: '進行中',\n  COMPLETED: '已完成',\n  SETTLED: '已分帳',\n};\n\nexport const MEMBER_LABELS: Record<MemberLevel, string> = {\n  PLAN_A: 'Plan A',\n  PLAN_B: 'Plan B',\n  PLAN_C: 'Plan C',\n  FULL: 'FULL',\n};\n\nexport const ROLE_LABELS: Record<UserRole, string> = {\n  MCLUB_STAFF: 'MCLUB Admin',\n  SME_OWNER: 'SME老闆',\n  AGENT: 'Agent',\n  END_USER: 'End User',\n};\n\nexport const EVENT_TYPE_ICONS: Record<string, string> = {\n  purchase: '🛒',\n  upgrade: '⬆️',\n  followup: '📞',\n  note: '📝',\n  status_change: '🔄',\n};\n</pre></body></html>",
    "title": "",
    "url": "https://raw.githubusercontent.com/mypathtravel101-cyber/mclub/main/src/components/mclub/types.ts",
    "usage": {
      "tokens": 1456
    }
  },
  "meta": {
    "usage": {
      "tokens": 1456
    }
  },
  "status": 20000
}